xiaomw/AI.py
xiaomw/__init__.py
xiaomw-0.1.0.dist-info/LICENSE.txt
xiaomw-0.1.0.dist-info/METADATA
xiaomw-0.1.0.dist-info/WHEEL
xiaomw-0.1.0.dist-info/top_level.txt
xiaomw-0.1.0.dist-info/RECORD
