Metadata-Version: 2.2
Name: xiaomw
Version: 0.1.0
Summary: A Python library for AI story generation
Home-page: https://github.com/Tonykai88/AI.git
Author: 何凯
Author-email: hekai@xiaoma.cn
Classifier: Programming Language :: Python :: 3
Classifier: License :: OSI Approved :: MIT License
Classifier: Operating System :: OS Independent
Requires-Python: >=3.6
License-File: LICENSE.txt
Requires-Dist: requests>=2.0.0
Dynamic: author
Dynamic: author-email
Dynamic: classifier
Dynamic: description
Dynamic: description-content-type
Dynamic: home-page
Dynamic: requires-dist
Dynamic: requires-python
Dynamic: summary
